setup.cfg
setup.py
zopyx.ep2011.egg-info/PKG-INFO
zopyx.ep2011.egg-info/SOURCES.txt
zopyx.ep2011.egg-info/dependency_links.txt
zopyx.ep2011.egg-info/entry_points.txt
zopyx.ep2011.egg-info/not-zip-safe
zopyx.ep2011.egg-info/requires.txt
zopyx.ep2011.egg-info/top_level.txt
zopyxep2011/__init__.py
zopyxep2011/countrys.json
zopyxep2011/data.csv
zopyxep2011/do_import.py