Metadata-Version: 1.0
Name: zopyx.ep2011
Version: 0.4.1
Summary: Europython MongoDB/Python training material
Home-page: UNKNOWN
Author: Andreas Jung
Author-email: info@zopyx.com
License: GPL
Platform: UNKNOWN
